<!--Transition Screen Location component://webroot/screen/webroot/SecondFactor.xml Transition Name actions--><transition name="actions"><actions><!--always-actions at component://webroot/screen/webroot.xml--><set field="html_scripts" from="new LinkedHashSet()"/><set field="footer_scripts" from="new LinkedHashSet()"/><set field="html_stylesheets" from="new LinkedHashSet()"/><!--pre-actions--><script><![CDATA[if (ec.user.userId || !ec.web.sessionAttributes.moquiAuthcFactorRequired) { sri.sendRedirectAndStopRender('/') }]]></script><!--actions--><service-call name="org.moqui.impl.UserServices.get#ExternalUserAuthcFactorInfo" out-map="context"/></actions></transition>