<!--Transition Screen Location component://SimpleScreens/screen/SimpleScreens/ProductStore/EditProductStore.xml Transition Name actions--><transition name="actions"><parameter name="productStoreId" required="true"/><parameter name="term"/><parameter name="facilityTypeEnumId"/><parameter name="parentFacilityId"/><parameter name="ownerPartyId"/><actions><!--always-actions at component://webroot/screen/webroot.xml--><set field="html_scripts" from="new LinkedHashSet()"/><set field="footer_scripts" from="new LinkedHashSet()"/><set field="html_stylesheets" from="new LinkedHashSet()"/><!--always-actions at component://PopCommerce/screen/PopCommerceAdmin.xml--><set field="appRoot" value="PopcAdmin"/><set field="searchIndexName" value="mantle"/><set field="searchLinkSets" value="PopcAdmin"/><set field="searchProductDocType" value="MantleProduct"/><set field="searchPartyDocType" value="MantleParty"/><set field="appUserGroupTypeEnumId" value="UgtPopcAdmin"/><service-call name="mantle.party.PartyServices.setup#UserOrganizationInfo" out-map="context"/><!--actions--><entity-find-one entity-name="mantle.product.store.ProductStore" value-field="store"><field-map field-name="productStoreId" from="productStoreId"/></entity-find-one><set field="localeStringList" from="[]"/><iterate list="Locale.getAvailableLocales()" entry="lcl"><script><![CDATA[if (lcl.toString()) localeStringList.add([locale:lcl.toString(), name:lcl.getDisplayName(ec.user.locale)])]]></script></iterate><order-map-list list="localeStringList"><order-by field-name="name"/></order-map-list></actions></transition>