<!--Service Location create#coarchy.ProcessStory--><service verb="create" noun="coarchy.ProcessStory"><in-parameters><parameter name="processStoryId" type="java.lang.String" required="true"/><parameter name="name" type="java.lang.String" required="false"/><parameter name="disabled" type="java.lang.String" required="false"/><parameter name="organizationId" type="java.lang.String" required="false"/></in-parameters><out-parameters><parameter name="processStoryId" type="java.lang.String" required="true"/></out-parameters><action><service-call name="create#coarchy.ProcessStory" in-map="[processStoryId:context.processStoryId,name:context.name,disabled:context.disabled,organizationId:context.organizationId]" out-map="[processStoryId:context.processStoryId]"/></action></service>