<!--Service Location create#mantle.account.invoice.InvoiceGlImpactSummary--><service verb="create" noun="mantle.account.invoice.InvoiceGlImpactSummary"><in-parameters><parameter name="itemDate" type="java.sql.Timestamp" required="false"/><parameter name="itemInvoiceDate" type="java.sql.Timestamp" required="false"/><parameter name="isAdjustment" type="java.lang.String" required="false"/><parameter name="itemsTotal" type="java.math.BigDecimal" required="false"/><parameter name="paymentId" type="java.lang.String" required="false"/><parameter name="appliedDate" type="java.sql.Timestamp" required="false"/><parameter name="amountApplied" type="java.math.BigDecimal" required="false"/><parameter name="unpaidAmount" type="java.math.BigDecimal" required="false"/><parameter name="toAppliedDate" type="java.sql.Timestamp" required="false"/><parameter name="toAmountApplied" type="java.math.BigDecimal" required="false"/><parameter name="totalAmountApplied" type="java.math.BigDecimal" required="false"/><parameter name="debitGlAccountClassEnumId" type="java.lang.String" required="false"/><parameter name="debitTransactionDate" type="java.sql.Timestamp" required="false"/><parameter name="debitDcFlag" type="java.lang.String" required="false"/><parameter name="debitTotal" type="java.math.BigDecimal" required="false"/><parameter name="creditGlAccountClassEnumId" type="java.lang.String" required="false"/><parameter name="creditTransactionDate" type="java.sql.Timestamp" required="false"/><parameter name="creditDcFlag" type="java.lang.String" required="false"/><parameter name="creditTotal" type="java.math.BigDecimal" required="false"/><parameter name="debitMinusCredit" type="java.math.BigDecimal" required="false"/><parameter name="creditMinusDebit" type="java.math.BigDecimal" required="false"/><parameter name="invoiceId" type="java.lang.String" required="true"/><parameter name="invoiceTypeEnumId" type="java.lang.String" required="false"/><parameter name="fromPartyId" type="java.lang.String" required="false"/><parameter name="toPartyId" type="java.lang.String" required="false"/><parameter name="statusId" type="java.lang.String" required="false"/><parameter name="billingAccountId" type="java.lang.String" required="false"/><parameter name="invoiceDate" type="java.sql.Timestamp" required="false"/><parameter name="dueDate" type="java.sql.Timestamp" required="false"/><parameter name="settlementTermId" type="java.lang.String" required="false"/><parameter name="paidDate" type="java.sql.Timestamp" required="false"/><parameter name="invoiceMessage" type="java.lang.String" required="false"/><parameter name="referenceNumber" type="java.lang.String" required="false"/><parameter name="otherPartyOrderId" type="java.lang.String" required="false"/><parameter name="description" type="java.lang.String" required="false"/><parameter name="currencyUomId" type="java.lang.String" required="false"/><parameter name="overrideOrgPartyId" type="java.lang.String" required="false"/><parameter name="productStoreId" type="java.lang.String" required="false"/><parameter name="partyRelationshipId" type="java.lang.String" required="false"/><parameter name="timePeriodId" type="java.lang.String" required="false"/><parameter name="acctgTransResultEnumId" type="java.lang.String" required="false"/><parameter name="systemMessageRemoteId" type="java.lang.String" required="false"/><parameter name="externalId" type="java.lang.String" required="false"/><parameter name="originId" type="java.lang.String" required="false"/><parameter name="invoiceTotal" type="java.math.BigDecimal" required="false"/><parameter name="appliedPaymentsTotal" type="java.math.BigDecimal" required="false"/><parameter name="unpaidTotal" type="java.math.BigDecimal" required="false"/></in-parameters><out-parameters><parameter name="invoiceId" type="java.lang.String" required="true"/></out-parameters><action><service-call name="create#mantle.account.invoice.InvoiceGlImpactSummary" in-map="[itemDate:context.itemDate,itemInvoiceDate:context.itemInvoiceDate,isAdjustment:context.isAdjustment,itemsTotal:context.itemsTotal,paymentId:context.paymentId,appliedDate:context.appliedDate,amountApplied:context.amountApplied,unpaidAmount:context.unpaidAmount,toAppliedDate:context.toAppliedDate,toAmountApplied:context.toAmountApplied,totalAmountApplied:context.totalAmountApplied,debitGlAccountClassEnumId:context.debitGlAccountClassEnumId,debitTransactionDate:context.debitTransactionDate,debitDcFlag:context.debitDcFlag,debitTotal:context.debitTotal,creditGlAccountClassEnumId:context.creditGlAccountClassEnumId,creditTransactionDate:context.creditTransactionDate,creditDcFlag:context.creditDcFlag,creditTotal:context.creditTotal,debitMinusCredit:context.debitMinusCredit,creditMinusDebit:context.creditMinusDebit,invoiceId:context.invoiceId,invoiceTypeEnumId:context.invoiceTypeEnumId,fromPartyId:context.fromPartyId,toPartyId:context.toPartyId,statusId:context.statusId,billingAccountId:context.billingAccountId,invoiceDate:context.invoiceDate,dueDate:context.dueDate,settlementTermId:context.settlementTermId,paidDate:context.paidDate,invoiceMessage:context.invoiceMessage,referenceNumber:context.referenceNumber,otherPartyOrderId:context.otherPartyOrderId,description:context.description,currencyUomId:context.currencyUomId,overrideOrgPartyId:context.overrideOrgPartyId,productStoreId:context.productStoreId,partyRelationshipId:context.partyRelationshipId,timePeriodId:context.timePeriodId,acctgTransResultEnumId:context.acctgTransResultEnumId,systemMessageRemoteId:context.systemMessageRemoteId,externalId:context.externalId,originId:context.originId,invoiceTotal:context.invoiceTotal,appliedPaymentsTotal:context.appliedPaymentsTotal,unpaidTotal:context.unpaidTotal]" out-map="[invoiceId:context.invoiceId]"/></action></service>