<!--Service Location create#mantle.product.ProductAssocSummary--><service verb="create" noun="mantle.product.ProductAssocSummary"><in-parameters><parameter name="bomQuantityTotal" type="java.math.BigDecimal" required="false"/><parameter name="productId" type="java.lang.String" required="true"/><parameter name="toProductId" type="java.lang.String" required="true"/><parameter name="productAssocTypeEnumId" type="java.lang.String" required="true"/><parameter name="fromDate" type="java.sql.Timestamp" required="true"/><parameter name="thruDate" type="java.sql.Timestamp" required="false"/><parameter name="sequenceNum" type="java.lang.Long" required="false"/><parameter name="reason" type="java.lang.String" required="false"/><parameter name="scrapFactor" type="java.math.BigDecimal" required="false"/><parameter name="instruction" type="java.lang.String" required="false"/><parameter name="routingWorkEffortId" type="java.lang.String" required="false"/></in-parameters><out-parameters><parameter name="productId" type="java.lang.String" required="true"/><parameter name="toProductId" type="java.lang.String" required="true"/><parameter name="productAssocTypeEnumId" type="java.lang.String" required="true"/><parameter name="fromDate" type="java.sql.Timestamp" required="true"/></out-parameters><action><service-call name="create#mantle.product.ProductAssocSummary" in-map="[bomQuantityTotal:context.bomQuantityTotal,productId:context.productId,toProductId:context.toProductId,productAssocTypeEnumId:context.productAssocTypeEnumId,fromDate:context.fromDate,thruDate:context.thruDate,sequenceNum:context.sequenceNum,reason:context.reason,scrapFactor:context.scrapFactor,instruction:context.instruction,routingWorkEffortId:context.routingWorkEffortId]" out-map="[productId:context.productId,toProductId:context.toProductId,productAssocTypeEnumId:context.productAssocTypeEnumId,fromDate:context.fromDate]"/></action></service>