<!--Service Location delete#mantle.work.effort.PartyTaskSummary--><service verb="delete" noun="mantle.work.effort.PartyTaskSummary"><in-parameters><parameter name="partyStatusId" type="java.lang.String" required="false"/><parameter name="teamMemberPartyId" type="java.lang.String" required="false"/><parameter name="assocFromDate" type="java.sql.Timestamp" required="true"/><parameter name="assocThruDate" type="java.sql.Timestamp" required="false"/><parameter name="workEffortId" type="java.lang.String" required="true"/><parameter name="universalId" type="java.lang.String" required="false"/><parameter name="sourceReferenceId" type="java.lang.String" required="false"/><parameter name="parentWorkEffortId" type="java.lang.String" required="false"/><parameter name="rootWorkEffortId" type="java.lang.String" required="false"/><parameter name="workEffortTypeEnumId" type="java.lang.String" required="false"/><parameter name="purposeEnumId" type="java.lang.String" required="false"/><parameter name="visibilityEnumId" type="java.lang.String" required="false"/><parameter name="resolutionEnumId" type="java.lang.String" required="false"/><parameter name="ownerPartyId" type="java.lang.String" required="false"/><parameter name="productStoreId" type="java.lang.String" required="false"/><parameter name="statusId" type="java.lang.String" required="false"/><parameter name="statusFlowId" type="java.lang.String" required="false"/><parameter name="priority" type="java.lang.Long" required="false"/><parameter name="sendNotificationEmail" type="java.lang.String" required="false"/><parameter name="percentComplete" type="java.lang.Long" required="false"/><parameter name="revisionNumber" type="java.lang.Long" required="false"/><parameter name="workEffortName" type="java.lang.String" required="false"/><parameter name="description" type="java.lang.String" required="false"/><parameter name="location" type="java.lang.String" required="false"/><parameter name="facilityId" type="java.lang.String" required="false"/><parameter name="infoUrl" type="java.lang.String" required="false"/><parameter name="shipmentMethodEnumId" type="java.lang.String" required="false"/><parameter name="estimatedStartDate" type="java.sql.Timestamp" required="false"/><parameter name="estimatedCompletionDate" type="java.sql.Timestamp" required="false"/><parameter name="actualStartDate" type="java.sql.Timestamp" required="false"/><parameter name="actualCompletionDate" type="java.sql.Timestamp" required="false"/><parameter name="recurStartCron" type="java.lang.String" required="false"/><parameter name="recurLimit" type="java.lang.Long" required="false"/><parameter name="recurEndDate" type="java.sql.Timestamp" required="false"/><parameter name="allDayStart" type="java.sql.Date" required="false"/><parameter name="allDayEnd" type="java.sql.Date" required="false"/><parameter name="estimatedWorkTime" type="java.math.BigDecimal" required="false"/><parameter name="estimatedSetupTime" type="java.math.BigDecimal" required="false"/><parameter name="remainingWorkTime" type="java.math.BigDecimal" required="false"/><parameter name="actualWorkTime" type="java.math.BigDecimal" required="false"/><parameter name="actualSetupTime" type="java.math.BigDecimal" required="false"/><parameter name="totalTimeAllowed" type="java.math.BigDecimal" required="false"/><parameter name="estimatedWorkDuration" type="java.math.BigDecimal" required="false"/><parameter name="actualWorkDuration" type="java.math.BigDecimal" required="false"/><parameter name="actualBreakDuration" type="java.math.BigDecimal" required="false"/><parameter name="timeUomId" type="java.lang.String" required="false"/><parameter name="actualCost" type="java.math.BigDecimal" required="false"/><parameter name="actualClientCost" type="java.math.BigDecimal" required="false"/><parameter name="totalClientCostAllowed" type="java.math.BigDecimal" required="false"/><parameter name="costUomId" type="java.lang.String" required="false"/><parameter name="activityId" type="java.lang.String" required="false"/><parameter name="milestoneWorkEffortId" type="java.lang.String" required="true"/><parameter name="milestoneUniversalId" type="java.lang.String" required="false"/><parameter name="milestoneSourceReferenceId" type="java.lang.String" required="false"/><parameter name="milestoneParentWorkEffortId" type="java.lang.String" required="false"/><parameter name="milestoneRootWorkEffortId" type="java.lang.String" required="false"/><parameter name="milestoneWorkEffortTypeEnumId" type="java.lang.String" required="false"/><parameter name="milestonePurposeEnumId" type="java.lang.String" required="false"/><parameter name="milestoneVisibilityEnumId" type="java.lang.String" required="false"/><parameter name="milestoneResolutionEnumId" type="java.lang.String" required="false"/><parameter name="milestoneWorkTypeEnumId" type="java.lang.String" required="false"/><parameter name="milestoneOwnerPartyId" type="java.lang.String" required="false"/><parameter name="milestoneProductStoreId" type="java.lang.String" required="false"/><parameter name="milestoneStatusId" type="java.lang.String" required="false"/><parameter name="milestoneStatusFlowId" type="java.lang.String" required="false"/><parameter name="milestonePriority" type="java.lang.Long" required="false"/><parameter name="milestoneSendNotificationEmail" type="java.lang.String" required="false"/><parameter name="milestonePercentComplete" type="java.lang.Long" required="false"/><parameter name="milestoneRevisionNumber" type="java.lang.Long" required="false"/><parameter name="milestoneWorkEffortName" type="java.lang.String" required="false"/><parameter name="milestoneDescription" type="java.lang.String" required="false"/><parameter name="milestoneLocation" type="java.lang.String" required="false"/><parameter name="milestoneFacilityId" type="java.lang.String" required="false"/><parameter name="milestoneInfoUrl" type="java.lang.String" required="false"/><parameter name="milestoneShipmentMethodEnumId" type="java.lang.String" required="false"/><parameter name="milestoneEstimatedStartDate" type="java.sql.Timestamp" required="false"/><parameter name="milestoneEstimatedCompletionDate" type="java.sql.Timestamp" required="false"/><parameter name="milestoneActualStartDate" type="java.sql.Timestamp" required="false"/><parameter name="milestoneActualCompletionDate" type="java.sql.Timestamp" required="false"/><parameter name="milestoneRecurStartCron" type="java.lang.String" required="false"/><parameter name="milestoneRecurLimit" type="java.lang.Long" required="false"/><parameter name="milestoneRecurEndDate" type="java.sql.Timestamp" required="false"/><parameter name="milestoneAllDayStart" type="java.sql.Date" required="false"/><parameter name="milestoneAllDayEnd" type="java.sql.Date" required="false"/><parameter name="milestoneEstimatedWorkTime" type="java.math.BigDecimal" required="false"/><parameter name="milestoneEstimatedSetupTime" type="java.math.BigDecimal" required="false"/><parameter name="milestoneRemainingWorkTime" type="java.math.BigDecimal" required="false"/><parameter name="milestoneActualWorkTime" type="java.math.BigDecimal" required="false"/><parameter name="milestoneActualSetupTime" type="java.math.BigDecimal" required="false"/><parameter name="milestoneTotalTimeAllowed" type="java.math.BigDecimal" required="false"/><parameter name="milestoneEstimatedWorkDuration" type="java.math.BigDecimal" required="false"/><parameter name="milestoneActualWorkDuration" type="java.math.BigDecimal" required="false"/><parameter name="milestoneActualBreakDuration" type="java.math.BigDecimal" required="false"/><parameter name="milestoneTimeUomId" type="java.lang.String" required="false"/><parameter name="milestoneActualCost" type="java.math.BigDecimal" required="false"/><parameter name="milestoneActualClientCost" type="java.math.BigDecimal" required="false"/><parameter name="milestoneTotalClientCostAllowed" type="java.math.BigDecimal" required="false"/><parameter name="milestoneCostUomId" type="java.lang.String" required="false"/><parameter name="milestoneActivityId" type="java.lang.String" required="false"/><parameter name="partyId" type="java.lang.String" required="true"/><parameter name="roleTypeId" type="java.lang.String" required="true"/><parameter name="fromDate" type="java.sql.Timestamp" required="true"/><parameter name="thruDate" type="java.sql.Timestamp" required="false"/><parameter name="availabilityEnumId" type="java.lang.String" required="false"/><parameter name="delegateReasonEnumId" type="java.lang.String" required="false"/><parameter name="expectationEnumId" type="java.lang.String" required="false"/><parameter name="workTypeEnumId" type="java.lang.String" required="false"/><parameter name="emplPositionClassId" type="java.lang.String" required="false"/><parameter name="emplPositionId" type="java.lang.String" required="false"/><parameter name="comments" type="java.lang.String" required="false"/><parameter name="mustRsvp" type="java.lang.String" required="false"/><parameter name="receiveNotifications" type="java.lang.String" required="false"/><parameter name="teamWorkEffortId" type="java.lang.String" required="true"/><parameter name="teamPartyId" type="java.lang.String" required="true"/><parameter name="teamRoleTypeId" type="java.lang.String" required="true"/><parameter name="teamFromDate" type="java.sql.Timestamp" required="true"/><parameter name="teamThruDate" type="java.sql.Timestamp" required="false"/><parameter name="teamStatusId" type="java.lang.String" required="false"/><parameter name="teamAvailabilityEnumId" type="java.lang.String" required="false"/><parameter name="teamDelegateReasonEnumId" type="java.lang.String" required="false"/><parameter name="teamExpectationEnumId" type="java.lang.String" required="false"/><parameter name="teamWorkTypeEnumId" type="java.lang.String" required="false"/><parameter name="teamEmplPositionClassId" type="java.lang.String" required="false"/><parameter name="teamEmplPositionId" type="java.lang.String" required="false"/><parameter name="teamComments" type="java.lang.String" required="false"/><parameter name="teamMustRsvp" type="java.lang.String" required="false"/><parameter name="teamReceiveNotifications" type="java.lang.String" required="false"/></in-parameters><out-parameters><parameter name="assocFromDate" type="java.sql.Timestamp" required="true"/><parameter name="workEffortId" type="java.lang.String" required="true"/><parameter name="milestoneWorkEffortId" type="java.lang.String" required="true"/><parameter name="partyId" type="java.lang.String" required="true"/><parameter name="roleTypeId" type="java.lang.String" required="true"/><parameter name="fromDate" type="java.sql.Timestamp" required="true"/><parameter name="teamWorkEffortId" type="java.lang.String" required="true"/><parameter name="teamPartyId" type="java.lang.String" required="true"/><parameter name="teamRoleTypeId" type="java.lang.String" required="true"/><parameter name="teamFromDate" type="java.sql.Timestamp" required="true"/></out-parameters><action><service-call name="delete#mantle.work.effort.PartyTaskSummary" in-map="[partyStatusId:context.partyStatusId,teamMemberPartyId:context.teamMemberPartyId,assocFromDate:context.assocFromDate,assocThruDate:context.assocThruDate,workEffortId:context.workEffortId,universalId:context.universalId,sourceReferenceId:context.sourceReferenceId,parentWorkEffortId:context.parentWorkEffortId,rootWorkEffortId:context.rootWorkEffortId,workEffortTypeEnumId:context.workEffortTypeEnumId,purposeEnumId:context.purposeEnumId,visibilityEnumId:context.visibilityEnumId,resolutionEnumId:context.resolutionEnumId,ownerPartyId:context.ownerPartyId,productStoreId:context.productStoreId,statusId:context.statusId,statusFlowId:context.statusFlowId,priority:context.priority,sendNotificationEmail:context.sendNotificationEmail,percentComplete:context.percentComplete,revisionNumber:context.revisionNumber,workEffortName:context.workEffortName,description:context.description,location:context.location,facilityId:context.facilityId,infoUrl:context.infoUrl,shipmentMethodEnumId:context.shipmentMethodEnumId,estimatedStartDate:context.estimatedStartDate,estimatedCompletionDate:context.estimatedCompletionDate,actualStartDate:context.actualStartDate,actualCompletionDate:context.actualCompletionDate,recurStartCron:context.recurStartCron,recurLimit:context.recurLimit,recurEndDate:context.recurEndDate,allDayStart:context.allDayStart,allDayEnd:context.allDayEnd,estimatedWorkTime:context.estimatedWorkTime,estimatedSetupTime:context.estimatedSetupTime,remainingWorkTime:context.remainingWorkTime,actualWorkTime:context.actualWorkTime,actualSetupTime:context.actualSetupTime,totalTimeAllowed:context.totalTimeAllowed,estimatedWorkDuration:context.estimatedWorkDuration,actualWorkDuration:context.actualWorkDuration,actualBreakDuration:context.actualBreakDuration,timeUomId:context.timeUomId,actualCost:context.actualCost,actualClientCost:context.actualClientCost,totalClientCostAllowed:context.totalClientCostAllowed,costUomId:context.costUomId,activityId:context.activityId,milestoneWorkEffortId:context.milestoneWorkEffortId,milestoneUniversalId:context.milestoneUniversalId,milestoneSourceReferenceId:context.milestoneSourceReferenceId,milestoneParentWorkEffortId:context.milestoneParentWorkEffortId,milestoneRootWorkEffortId:context.milestoneRootWorkEffortId,milestoneWorkEffortTypeEnumId:context.milestoneWorkEffortTypeEnumId,milestonePurposeEnumId:context.milestonePurposeEnumId,milestoneVisibilityEnumId:context.milestoneVisibilityEnumId,milestoneResolutionEnumId:context.milestoneResolutionEnumId,milestoneWorkTypeEnumId:context.milestoneWorkTypeEnumId,milestoneOwnerPartyId:context.milestoneOwnerPartyId,milestoneProductStoreId:context.milestoneProductStoreId,milestoneStatusId:context.milestoneStatusId,milestoneStatusFlowId:context.milestoneStatusFlowId,milestonePriority:context.milestonePriority,milestoneSendNotificationEmail:context.milestoneSendNotificationEmail,milestonePercentComplete:context.milestonePercentComplete,milestoneRevisionNumber:context.milestoneRevisionNumber,milestoneWorkEffortName:context.milestoneWorkEffortName,milestoneDescription:context.milestoneDescription,milestoneLocation:context.milestoneLocation,milestoneFacilityId:context.milestoneFacilityId,milestoneInfoUrl:context.milestoneInfoUrl,milestoneShipmentMethodEnumId:context.milestoneShipmentMethodEnumId,milestoneEstimatedStartDate:context.milestoneEstimatedStartDate,milestoneEstimatedCompletionDate:context.milestoneEstimatedCompletionDate,milestoneActualStartDate:context.milestoneActualStartDate,milestoneActualCompletionDate:context.milestoneActualCompletionDate,milestoneRecurStartCron:context.milestoneRecurStartCron,milestoneRecurLimit:context.milestoneRecurLimit,milestoneRecurEndDate:context.milestoneRecurEndDate,milestoneAllDayStart:context.milestoneAllDayStart,milestoneAllDayEnd:context.milestoneAllDayEnd,milestoneEstimatedWorkTime:context.milestoneEstimatedWorkTime,milestoneEstimatedSetupTime:context.milestoneEstimatedSetupTime,milestoneRemainingWorkTime:context.milestoneRemainingWorkTime,milestoneActualWorkTime:context.milestoneActualWorkTime,milestoneActualSetupTime:context.milestoneActualSetupTime,milestoneTotalTimeAllowed:context.milestoneTotalTimeAllowed,milestoneEstimatedWorkDuration:context.milestoneEstimatedWorkDuration,milestoneActualWorkDuration:context.milestoneActualWorkDuration,milestoneActualBreakDuration:context.milestoneActualBreakDuration,milestoneTimeUomId:context.milestoneTimeUomId,milestoneActualCost:context.milestoneActualCost,milestoneActualClientCost:context.milestoneActualClientCost,milestoneTotalClientCostAllowed:context.milestoneTotalClientCostAllowed,milestoneCostUomId:context.milestoneCostUomId,milestoneActivityId:context.milestoneActivityId,partyId:context.partyId,roleTypeId:context.roleTypeId,fromDate:context.fromDate,thruDate:context.thruDate,availabilityEnumId:context.availabilityEnumId,delegateReasonEnumId:context.delegateReasonEnumId,expectationEnumId:context.expectationEnumId,workTypeEnumId:context.workTypeEnumId,emplPositionClassId:context.emplPositionClassId,emplPositionId:context.emplPositionId,comments:context.comments,mustRsvp:context.mustRsvp,receiveNotifications:context.receiveNotifications,teamWorkEffortId:context.teamWorkEffortId,teamPartyId:context.teamPartyId,teamRoleTypeId:context.teamRoleTypeId,teamFromDate:context.teamFromDate,teamThruDate:context.teamThruDate,teamStatusId:context.teamStatusId,teamAvailabilityEnumId:context.teamAvailabilityEnumId,teamDelegateReasonEnumId:context.teamDelegateReasonEnumId,teamExpectationEnumId:context.teamExpectationEnumId,teamWorkTypeEnumId:context.teamWorkTypeEnumId,teamEmplPositionClassId:context.teamEmplPositionClassId,teamEmplPositionId:context.teamEmplPositionId,teamComments:context.teamComments,teamMustRsvp:context.teamMustRsvp,teamReceiveNotifications:context.teamReceiveNotifications]" out-map="[assocFromDate:context.assocFromDate,workEffortId:context.workEffortId,milestoneWorkEffortId:context.milestoneWorkEffortId,partyId:context.partyId,roleTypeId:context.roleTypeId,fromDate:context.fromDate,teamWorkEffortId:context.teamWorkEffortId,teamPartyId:context.teamPartyId,teamRoleTypeId:context.teamRoleTypeId,teamFromDate:context.teamFromDate]"/></action></service>