<!--Service Location delete#mantle.product.store.ProductStoreSettingLookup--><service verb="delete" noun="mantle.product.store.ProductStoreSettingLookup"><in-parameters><parameter name="orderId" type="java.lang.String" required="true"/><parameter name="shipmentId" type="java.lang.String" required="false"/><parameter name="productStoreId" type="java.lang.String" required="true"/><parameter name="settingTypeEnumId" type="java.lang.String" required="true"/><parameter name="fromDate" type="java.sql.Timestamp" required="true"/><parameter name="thruDate" type="java.sql.Timestamp" required="false"/><parameter name="settingValue" type="java.lang.String" required="false"/></in-parameters><out-parameters><parameter name="orderId" type="java.lang.String" required="true"/><parameter name="productStoreId" type="java.lang.String" required="true"/><parameter name="settingTypeEnumId" type="java.lang.String" required="true"/><parameter name="fromDate" type="java.sql.Timestamp" required="true"/></out-parameters><action><service-call name="delete#mantle.product.store.ProductStoreSettingLookup" in-map="[orderId:context.orderId,shipmentId:context.shipmentId,productStoreId:context.productStoreId,settingTypeEnumId:context.settingTypeEnumId,fromDate:context.fromDate,thruDate:context.thruDate,settingValue:context.settingValue]" out-map="[orderId:context.orderId,productStoreId:context.productStoreId,settingTypeEnumId:context.settingTypeEnumId,fromDate:context.fromDate]"/></action></service>