<!--Service Location delete#moqui.service.job.ServiceJobRun--><service verb="delete" noun="moqui.service.job.ServiceJobRun"><in-parameters><parameter name="jobRunId" type="java.lang.String" required="true"/><parameter name="jobName" type="java.lang.String" required="false"/><parameter name="userId" type="java.lang.String" required="false"/><parameter name="parameters" type="java.lang.String" required="false"/><parameter name="results" type="java.lang.String" required="false"/><parameter name="messages" type="java.lang.String" required="false"/><parameter name="hasError" type="java.lang.String" required="false"/><parameter name="errors" type="java.lang.String" required="false"/><parameter name="hostAddress" type="java.lang.String" required="false"/><parameter name="hostName" type="java.lang.String" required="false"/><parameter name="runThread" type="java.lang.String" required="false"/><parameter name="startTime" type="java.sql.Timestamp" required="false"/><parameter name="endTime" type="java.sql.Timestamp" required="false"/></in-parameters><out-parameters><parameter name="jobRunId" type="java.lang.String" required="true"/></out-parameters><action><service-call name="delete#moqui.service.job.ServiceJobRun" in-map="[jobRunId:context.jobRunId,jobName:context.jobName,userId:context.userId,parameters:context.parameters,results:context.results,messages:context.messages,hasError:context.hasError,errors:context.errors,hostAddress:context.hostAddress,hostName:context.hostName,runThread:context.runThread,startTime:context.startTime,endTime:context.endTime]" out-map="[jobRunId:context.jobRunId]"/></action></service>