<!--Service Location delete#mantle.order.OrderItemBilling--><service verb="delete" noun="mantle.order.OrderItemBilling"><in-parameters><parameter name="orderItemBillingId" type="java.lang.String" required="true"/><parameter name="orderId" type="java.lang.String" required="false"/><parameter name="orderItemSeqId" type="java.lang.String" required="false"/><parameter name="invoiceId" type="java.lang.String" required="false"/><parameter name="invoiceItemSeqId" type="java.lang.String" required="false"/><parameter name="assetIssuanceId" type="java.lang.String" required="false"/><parameter name="assetReceiptId" type="java.lang.String" required="false"/><parameter name="shipmentId" type="java.lang.String" required="false"/><parameter name="quantity" type="java.math.BigDecimal" required="false"/><parameter name="amount" type="java.math.BigDecimal" required="false"/></in-parameters><out-parameters><parameter name="orderItemBillingId" type="java.lang.String" required="true"/></out-parameters><action><service-call name="delete#mantle.order.OrderItemBilling" in-map="[orderItemBillingId:context.orderItemBillingId,orderId:context.orderId,orderItemSeqId:context.orderItemSeqId,invoiceId:context.invoiceId,invoiceItemSeqId:context.invoiceItemSeqId,assetIssuanceId:context.assetIssuanceId,assetReceiptId:context.assetReceiptId,shipmentId:context.shipmentId,quantity:context.quantity,amount:context.amount]" out-map="[orderItemBillingId:context.orderItemBillingId]"/></action></service>