<!--Service Location delete#mantle.party.time.TimePeriodAndType--><service verb="delete" noun="mantle.party.time.TimePeriodAndType"><in-parameters><parameter name="timePeriodId" type="java.lang.String" required="true"/><parameter name="parentPeriodId" type="java.lang.String" required="false"/><parameter name="previousPeriodId" type="java.lang.String" required="false"/><parameter name="timePeriodTypeId" type="java.lang.String" required="false"/><parameter name="partyId" type="java.lang.String" required="false"/><parameter name="periodNum" type="java.lang.Long" required="false"/><parameter name="periodName" type="java.lang.String" required="false"/><parameter name="fromDate" type="java.sql.Date" required="false"/><parameter name="thruDate" type="java.sql.Date" required="false"/><parameter name="isClosed" type="java.lang.String" required="false"/><parameter name="periodPurposeEnumId" type="java.lang.String" required="false"/><parameter name="parentPeriodTypeId" type="java.lang.String" required="false"/><parameter name="description" type="java.lang.String" required="false"/><parameter name="periodLength" type="java.math.BigDecimal" required="false"/><parameter name="lengthUomId" type="java.lang.String" required="false"/></in-parameters><out-parameters><parameter name="timePeriodId" type="java.lang.String" required="true"/></out-parameters><action><service-call name="delete#mantle.party.time.TimePeriodAndType" in-map="[timePeriodId:context.timePeriodId,parentPeriodId:context.parentPeriodId,previousPeriodId:context.previousPeriodId,timePeriodTypeId:context.timePeriodTypeId,partyId:context.partyId,periodNum:context.periodNum,periodName:context.periodName,fromDate:context.fromDate,thruDate:context.thruDate,isClosed:context.isClosed,periodPurposeEnumId:context.periodPurposeEnumId,parentPeriodTypeId:context.parentPeriodTypeId,description:context.description,periodLength:context.periodLength,lengthUomId:context.lengthUomId]" out-map="[timePeriodId:context.timePeriodId]"/></action></service>