<!--Service Location mantle.shipment.ShipmentServices.delete#ShipmentPackage--><service verb="delete" noun="ShipmentPackage"><in-parameters><parameter name="shipmentId" required="true" entity-name="mantle.shipment.ShipmentPackage" field-name="shipmentId"/><parameter name="shipmentPackageSeqId" required="true" entity-name="mantle.shipment.ShipmentPackage" field-name="shipmentPackageSeqId"/></in-parameters><out-parameters/><actions><entity-find entity-name="mantle.shipment.ShipmentPackageContent" list="packageContentList"><econdition field-name="shipmentId"/><econdition field-name="shipmentPackageSeqId"/></entity-find><if condition="packageContentList"><return error="true" message="Cannot delete package ${shipmentPackageSeqId}, has items in it"/></if><entity-delete-by-condition entity-name="mantle.shipment.ShipmentPackageRouteSeg"><econdition field-name="shipmentId"/><econdition field-name="shipmentPackageSeqId"/></entity-delete-by-condition><entity-delete-by-condition entity-name="mantle.shipment.ShipmentPackage"><econdition field-name="shipmentId"/><econdition field-name="shipmentPackageSeqId"/></entity-delete-by-condition></actions></service>