<!--Service Location org.moqui.impl.ScreenServices.delete#FormResponse--><service verb="delete" noun="FormResponse"><in-parameters><parameter name="formResponseId" required="true" entity-name="moqui.screen.form.FormResponse" field-name="formResponseId"/></in-parameters><out-parameters/><actions><entity-find-one entity-name="moqui.screen.form.FormResponse" value-field="formResponse"/><if condition="formResponse == null"><return message="Form Response ${formResponseId} not found"/></if><entity-delete-by-condition entity-name="moqui.screen.form.FormResponseAnswer"><econdition field-name="formResponseId"/></entity-delete-by-condition><entity-delete value-field="formResponse"/></actions></service>