<!--Service Location sales.SalesOrderServices.update#BillToContactMech--><service verb="update" noun="BillToContactMech"><in-parameters><parameter name="orderId"/><parameter name="orderPartSeqId"/><parameter name="billToPostalContactMechId"/></in-parameters><out-parameters/><actions><service-call name="delete#mantle.order.OrderPartContactMech"><field-map field-name="orderId" from="orderId"/><field-map field-name="orderPartSeqId" from="orderPartSeqId"/><field-map field-name="contactMechPurposeId" value="PostalBilling"/><field-map field-name="contactMechId" value="*"/></service-call><service-call name="create#mantle.order.OrderPartContactMech"><field-map field-name="orderId" from="orderId"/><field-map field-name="orderPartSeqId" from="orderPartSeqId"/><field-map field-name="contactMechPurposeId" value="PostalBilling"/><field-map field-name="contactMechId" from="billToPostalContactMechId"/></service-call></actions></service>