<!--Service Location store#mantle.humanres.employment.WorkTypeRiskClass--><service verb="store" noun="mantle.humanres.employment.WorkTypeRiskClass"><in-parameters><parameter name="geoId" type="java.lang.String" required="true"/><parameter name="workTypeEnumId" type="java.lang.String" required="true"/><parameter name="riskClassEnumId" type="java.lang.String" required="false"/></in-parameters><out-parameters><parameter name="geoId" type="java.lang.String" required="true"/><parameter name="workTypeEnumId" type="java.lang.String" required="true"/></out-parameters><action><service-call name="store#mantle.humanres.employment.WorkTypeRiskClass" in-map="[geoId:context.geoId,workTypeEnumId:context.workTypeEnumId,riskClassEnumId:context.riskClassEnumId]" out-map="[geoId:context.geoId,workTypeEnumId:context.workTypeEnumId]"/></action></service>