<!--Service Location store#moqui.basic.GeoPoint--><service verb="store" noun="moqui.basic.GeoPoint"><in-parameters><parameter name="geoPointId" type="java.lang.String" required="true"/><parameter name="geoPointTypeEnumId" type="java.lang.String" required="false"/><parameter name="description" type="java.lang.String" required="false"/><parameter name="dataSourceId" type="java.lang.String" required="false"/><parameter name="latitude" type="java.lang.Double" required="false"/><parameter name="longitude" type="java.lang.Double" required="false"/><parameter name="elevation" type="java.lang.Double" required="false"/><parameter name="elevationUomId" type="java.lang.String" required="false"/><parameter name="information" type="java.lang.String" required="false"/></in-parameters><out-parameters><parameter name="geoPointId" type="java.lang.String" required="true"/></out-parameters><action><service-call name="store#moqui.basic.GeoPoint" in-map="[geoPointId:context.geoPointId,geoPointTypeEnumId:context.geoPointTypeEnumId,description:context.description,dataSourceId:context.dataSourceId,latitude:context.latitude,longitude:context.longitude,elevation:context.elevation,elevationUomId:context.elevationUomId,information:context.information]" out-map="[geoPointId:context.geoPointId]"/></action></service>