<!--Service Location store#mantle.product.category.ProductCategoryContent--><service verb="store" noun="mantle.product.category.ProductCategoryContent"><in-parameters><parameter name="productCategoryContentId" type="java.lang.String" required="true"/><parameter name="productCategoryId" type="java.lang.String" required="false"/><parameter name="contentLocation" type="java.lang.String" required="false"/><parameter name="categoryContentTypeEnumId" type="java.lang.String" required="false"/><parameter name="productStoreId" type="java.lang.String" required="false"/><parameter name="fromDate" type="java.sql.Timestamp" required="false"/><parameter name="thruDate" type="java.sql.Timestamp" required="false"/><parameter name="locale" type="java.lang.String" required="false"/><parameter name="description" type="java.lang.String" required="false"/><parameter name="sequenceNum" type="java.lang.Long" required="false"/><parameter name="userId" type="java.lang.String" required="false"/></in-parameters><out-parameters><parameter name="productCategoryContentId" type="java.lang.String" required="true"/></out-parameters><action><service-call name="store#mantle.product.category.ProductCategoryContent" in-map="[productCategoryContentId:context.productCategoryContentId,productCategoryId:context.productCategoryId,contentLocation:context.contentLocation,categoryContentTypeEnumId:context.categoryContentTypeEnumId,productStoreId:context.productStoreId,fromDate:context.fromDate,thruDate:context.thruDate,locale:context.locale,description:context.description,sequenceNum:context.sequenceNum,userId:context.userId]" out-map="[productCategoryContentId:context.productCategoryContentId]"/></action></service>