<!--Service Location update#mantle.party.PartyClassification--><service verb="update" noun="mantle.party.PartyClassification"><in-parameters><parameter name="partyClassificationId" type="java.lang.String" required="true"/><parameter name="classificationTypeEnumId" type="java.lang.String" required="false"/><parameter name="parentClassificationId" type="java.lang.String" required="false"/><parameter name="description" type="java.lang.String" required="false"/><parameter name="standardCode" type="java.lang.String" required="false"/></in-parameters><out-parameters><parameter name="partyClassificationId" type="java.lang.String" required="true"/></out-parameters><action><service-call name="update#mantle.party.PartyClassification" in-map="[partyClassificationId:context.partyClassificationId,classificationTypeEnumId:context.classificationTypeEnumId,parentClassificationId:context.parentClassificationId,description:context.description,standardCode:context.standardCode]" out-map="[partyClassificationId:context.partyClassificationId]"/></action></service>