<!--Service Location update#mantle.product.ProductDimensionAndType--><service verb="update" noun="mantle.product.ProductDimensionAndType"><in-parameters><parameter name="productId" type="java.lang.String" required="true"/><parameter name="dimensionTypeId" type="java.lang.String" required="true"/><parameter name="value" type="java.math.BigDecimal" required="false"/><parameter name="valueUomId" type="java.lang.String" required="false"/><parameter name="description" type="java.lang.String" required="false"/><parameter name="uomTypeEnumId" type="java.lang.String" required="false"/><parameter name="defaultUomId" type="java.lang.String" required="false"/><parameter name="uomUomId" type="java.lang.String" required="true"/><parameter name="uomUomTypeEnumId" type="java.lang.String" required="false"/><parameter name="uomAbbreviation" type="java.lang.String" required="false"/><parameter name="uomDescription" type="java.lang.String" required="false"/><parameter name="uomFractionDigits" type="java.lang.Long" required="false"/><parameter name="uomSymbol" type="java.lang.String" required="false"/></in-parameters><out-parameters><parameter name="productId" type="java.lang.String" required="true"/><parameter name="dimensionTypeId" type="java.lang.String" required="true"/><parameter name="uomUomId" type="java.lang.String" required="true"/></out-parameters><action><service-call name="update#mantle.product.ProductDimensionAndType" in-map="[productId:context.productId,dimensionTypeId:context.dimensionTypeId,value:context.value,valueUomId:context.valueUomId,description:context.description,uomTypeEnumId:context.uomTypeEnumId,defaultUomId:context.defaultUomId,uomUomId:context.uomUomId,uomUomTypeEnumId:context.uomUomTypeEnumId,uomAbbreviation:context.uomAbbreviation,uomDescription:context.uomDescription,uomFractionDigits:context.uomFractionDigits,uomSymbol:context.uomSymbol]" out-map="[productId:context.productId,dimensionTypeId:context.dimensionTypeId,uomUomId:context.uomUomId]"/></action></service>