<!--Service Location update#mantle.party.PartyIdentification--><service verb="update" noun="mantle.party.PartyIdentification"><in-parameters><parameter name="partyId" type="java.lang.String" required="true"/><parameter name="partyIdTypeEnumId" type="java.lang.String" required="true"/><parameter name="idValue" type="java.lang.String" required="false"/><parameter name="issuedBy" type="java.lang.String" required="false"/><parameter name="issuedByPartyId" type="java.lang.String" required="false"/><parameter name="expireDate" type="java.sql.Date" required="false"/></in-parameters><out-parameters><parameter name="partyId" type="java.lang.String" required="true"/><parameter name="partyIdTypeEnumId" type="java.lang.String" required="true"/></out-parameters><action><service-call name="update#mantle.party.PartyIdentification" in-map="[partyId:context.partyId,partyIdTypeEnumId:context.partyIdTypeEnumId,idValue:context.idValue,issuedBy:context.issuedBy,issuedByPartyId:context.issuedByPartyId,expireDate:context.expireDate]" out-map="[partyId:context.partyId,partyIdTypeEnumId:context.partyIdTypeEnumId]"/></action></service>